fncore/__init__.py
fncore/fn.py
fncore-2020.1.dist-info/LICENSE
fncore-2020.1.dist-info/METADATA
fncore-2020.1.dist-info/WHEEL
fncore-2020.1.dist-info/top_level.txt
fncore-2020.1.dist-info/RECORD
